wonda/__init__.py
wonda/modules.py
wonda/api/__init__.py
wonda/api/abc.py
wonda/api/api.py
wonda/api/poller/__init__.py
wonda/api/poller/abc.py
wonda/api/poller/default.py
wonda/api/poller/options.py
wonda/api/utils/__init__.py
wonda/api/utils/file_util.py
wonda/api/utils/token_util.py
wonda/bot/__init__.py
wonda/bot/abc.py
wonda/bot/bot.py
wonda/bot/blueprint/__init__.py
wonda/bot/blueprint/abc.py
wonda/bot/blueprint/default.py
wonda/bot/dispatch/__init__.py
wonda/bot/dispatch/dispatcher/__init__.py
wonda/bot/dispatch/dispatcher/abc.py
wonda/bot/dispatch/dispatcher/default.py
wonda/bot/dispatch/dispatcher/utils.py
wonda/bot/dispatch/handler/__init__.py
wonda/bot/dispatch/handler/abc.py
wonda/bot/dispatch/handler/func.py
wonda/bot/dispatch/middleware/__init__.py
wonda/bot/dispatch/middleware/abc.py
wonda/bot/dispatch/router/__init__.py
wonda/bot/dispatch/router/abc.py
wonda/bot/dispatch/router/default.py
wonda/bot/dispatch/view/__init__.py
wonda/bot/dispatch/view/abc.py
wonda/bot/dispatch/view/default.py
wonda/bot/dispatch/view/utils.py
wonda/bot/rules/__init__.py
wonda/bot/rules/abc.py
wonda/bot/rules/generic.py
wonda/bot/rules/message.py
wonda/bot/states/__init__.py
wonda/bot/states/types.py
wonda/bot/states/manager/__init__.py
wonda/bot/states/manager/abc.py
wonda/bot/states/manager/default.py
wonda/bot/updates/__init__.py
wonda/bot/updates/base.py
wonda/bot/updates/types.py
wonda/contrib/__init__.py
wonda/contrib/middleware/__init__.py
wonda/contrib/middleware/internationalization.py
wonda/contrib/middleware/rate_limiting.py
wonda/contrib/rules/__init__.py
wonda/contrib/rules/match.py
wonda/contrib/storage/__init__.py
wonda/contrib/storage/redis.py
wonda/errors/__init__.py
wonda/errors/internal.py
wonda/errors/external/__init__.py
wonda/errors/external/api.py
wonda/errors/external/code.py
wonda/errors/handler/__init__.py
wonda/errors/handler/abc.py
wonda/errors/handler/default.py
wonda/net/__init__.py
wonda/net/abc.py
wonda/net/default.py
wonda-0.7.10.dist-info/METADATA
wonda-0.7.10.dist-info/WHEEL
wonda-0.7.10.dist-info/licenses/LICENSE
wonda-0.7.10.dist-info/RECORD
