Metadata-Version: 2.4
Name: wonda
Version: 0.7.10
Summary: A light, blazing fast framework for developing capable bots.
License-Expression: MIT
License-File: LICENSE
Requires-Python: >=3.10
Requires-Dist: aiohttp>=3.11.11
Requires-Dist: certifi>=2025.1.31
Requires-Dist: msgspec>=0.19.0
Requires-Dist: structlog>=25.1.0
